odoo10_addon_account_invoice_qweb_operating_unit-10.0.1.0.0-py2.7-nspkg.pth
odoo/addons/account_invoice_qweb_operating_unit/README.rst
odoo/addons/account_invoice_qweb_operating_unit/__init__.py
odoo/addons/account_invoice_qweb_operating_unit/__manifest__.py
odoo/addons/account_invoice_qweb_operating_unit/views/report_account_invoice_qweb.xml
odoo10_addon_account_invoice_qweb_operating_unit-10.0.1.0.0.dist-info/DESCRIPTION.rst
odoo10_addon_account_invoice_qweb_operating_unit-10.0.1.0.0.dist-info/METADATA
odoo10_addon_account_invoice_qweb_operating_unit-10.0.1.0.0.dist-info/RECORD
odoo10_addon_account_invoice_qweb_operating_unit-10.0.1.0.0.dist-info/WHEEL
odoo10_addon_account_invoice_qweb_operating_unit-10.0.1.0.0.dist-info/metadata.json
odoo10_addon_account_invoice_qweb_operating_unit-10.0.1.0.0.dist-info/namespace_packages.txt
odoo10_addon_account_invoice_qweb_operating_unit-10.0.1.0.0.dist-info/top_level.txt
